crouton_client/UUID.py
crouton_client/__init__.py
crouton_client/async.py
crouton_client/blocking.py
crouton_client/client.py
crouton_client-0.1.6.dist-info/METADATA
crouton_client-0.1.6.dist-info/WHEEL
crouton_client-0.1.6.dist-info/RECORD
