Metadata-Version: 2.3
Name: crouton_client
Version: 0.1.6
Summary: A client for Swarmauri's crouton.
License: Apache-2.0
Author: Jacob Stewart
Author-email: jacob@swarmauri.com
Requires-Python: >=3.10,<4.0
Classifier: License :: OSI Approved :: Apache Software License
Classifier: Programming Language :: Python :: 3
Classifier: Programming Language :: Python :: 3.10
Classifier: Programming Language :: Python :: 3.11
Classifier: Programming Language :: Python :: 3.12
Classifier: Programming Language :: Python :: 3.13
Requires-Dist: httpx
Requires-Dist: pydantic
Requires-Dist: requests
Project-URL: Repository, https://github.com/swarmauri/crouton
